odoo/addons/partner_invoicing_mode/README.rst
odoo/addons/partner_invoicing_mode/__init__.py
odoo/addons/partner_invoicing_mode/__manifest__.py
odoo/addons/partner_invoicing_mode/data/ir_cron.xml
odoo/addons/partner_invoicing_mode/data/queue_job_data.xml
odoo/addons/partner_invoicing_mode/i18n/es.po
odoo/addons/partner_invoicing_mode/i18n/it.po
odoo/addons/partner_invoicing_mode/i18n/partner_invoicing_mode.pot
odoo/addons/partner_invoicing_mode/models/__init__.py
odoo/addons/partner_invoicing_mode/models/account_invoice.py
odoo/addons/partner_invoicing_mode/models/queue_job.py
odoo/addons/partner_invoicing_mode/models/res_company.py
odoo/addons/partner_invoicing_mode/models/res_config_settings.py
odoo/addons/partner_invoicing_mode/models/res_partner.py
odoo/addons/partner_invoicing_mode/models/sale_order.py
odoo/addons/partner_invoicing_mode/readme/CONTRIBUTORS.md
odoo/addons/partner_invoicing_mode/readme/CREDITS.md
odoo/addons/partner_invoicing_mode/readme/DESCRIPTION.md
odoo/addons/partner_invoicing_mode/readme/USAGE.md
odoo/addons/partner_invoicing_mode/static/description/icon.png
odoo/addons/partner_invoicing_mode/static/description/index.html
odoo/addons/partner_invoicing_mode/tests/__init__.py
odoo/addons/partner_invoicing_mode/tests/common.py
odoo/addons/partner_invoicing_mode/tests/test_invoice_mode.py
odoo/addons/partner_invoicing_mode/views/res_config_settings.xml
odoo/addons/partner_invoicing_mode/views/res_partner.xml
odoo/addons/partner_invoicing_mode/views/sale_order.xml
odoo_addon_partner_invoicing_mode-18.0.1.0.0.3.dist-info/METADATA
odoo_addon_partner_invoicing_mode-18.0.1.0.0.3.dist-info/WHEEL
odoo_addon_partner_invoicing_mode-18.0.1.0.0.3.dist-info/top_level.txt
odoo_addon_partner_invoicing_mode-18.0.1.0.0.3.dist-info/RECORD
